gortz/__init__.py
gortz/__main__.py
gortz/example.py
gortz-0.1.0.dist-info/entry_points.txt
gortz-0.1.0.dist-info/LICENSE
gortz-0.1.0.dist-info/WHEEL
gortz-0.1.0.dist-info/METADATA
gortz-0.1.0.dist-info/RECORD
